sinetstreamplugin/valuetype/ndarray.py
sinetstream_type_ndarray-1.9.2.dist-info/METADATA
sinetstream_type_ndarray-1.9.2.dist-info/WHEEL
sinetstream_type_ndarray-1.9.2.dist-info/entry_points.txt
sinetstream_type_ndarray-1.9.2.dist-info/RECORD
